gooeypie/__init__.py
gooeypie/containers.py
gooeypie/error.py
gooeypie/timer.py
gooeypie/widgets.py
gooeypie-0.13.0.dist-info/LICENSE.txt
gooeypie-0.13.0.dist-info/METADATA
gooeypie-0.13.0.dist-info/WHEEL
gooeypie-0.13.0.dist-info/top_level.txt
gooeypie-0.13.0.dist-info/RECORD
