Metadata-Version: 2.1
Name: gooeypie
Version: 0.13.0
Summary: Designed for beginners, GooeyPie is a simple but powerful GUI library.
Home-page: https://gooeypie.dev
Author: Adam Antonio
Author-email: adam@gooeypie.dev
License: MIT
Classifier: Development Status :: 4 - Beta
Classifier: License :: OSI Approved :: MIT License
Classifier: Programming Language :: Python
Classifier: Programming Language :: Python :: 3
Classifier: Topic :: Education
Classifier: Topic :: Software Development
Classifier: Topic :: Software Development :: User Interfaces
License-File: LICENSE.txt
Requires-Dist: pillow
